{
    "list": [
        null,
        "点击事件",
        "鼠标悬停",
        "鼠标离开",
        "显示时",
        "消失时",
        "左键按下",
        "左键弹起",
        "左键双击",
        "鼠标移动",
        "右键按下",
        "右键弹起",
        "右键点击"
    ],
    "data": [
        null,
        {
            "id": 1,
            "tips": "鼠标左键点击该组件时触发的事件\n触发者：玩家的对象  执行者：当前的对象",
            "multiline": false
        },
        {
            "id": 2,
            "tips": "鼠标悬停在该组件上时触发的事件\n触发者：玩家的对象  执行者：当前的对象",
            "multiline": false
        },
        {
            "id": 3,
            "tips": "鼠标从该组件中离开时触发的事件\n触发者：玩家的对象  执行者：当前的对象"
        },
        {
            "id": 4,
            "tips": "该组件显示时触发的事件\n触发者：玩家的对象  执行者：当前的对象"
        },
        {
            "id": 5,
            "tips": "该组件从显示状态消失时触发的事件\n触发者：玩家的对象  执行者：当前的对象"
        },
        {
            "id": 6,
            "tips": "鼠标左键按下该组件时触发的事件\n触发者：玩家的对象  执行者：当前的对象"
        },
        {
            "id": 7,
            "tips": "鼠标左键弹起该组件时触发的事件\n触发者：玩家的对象  执行者：当前的对象"
        },
        {
            "id": 8,
            "tips": "鼠标左键双击该组件触发的事件\n触发者：玩家的对象  执行者：当前的对象"
        },
        {
            "id": 9,
            "tips": "鼠标在该组件上移动时触发的事件\n触发者：玩家的对象  执行者：当前的对象"
        },
        {
            "id": 10,
            "tips": "鼠标右键按下该组件时触发的事件\n触发者：玩家的对象  执行者：当前的对象"
        },
        {
            "id": 11,
            "tips": "鼠标右键弹起该组件时触发的事件\n触发者：玩家的对象  执行者：当前的对象"
        },
        {
            "id": 12,
            "tips": "鼠标右键点击该组件时触发的事件\n触发者：玩家的对象  执行者：当前的对象"
        }
    ]
}